{
  "data": {
    "config": {
      "login_email": "E-Mail",
      "login_pwd": "Password",
      "login_sign_in": "Sign In",
      "login_forgot_pwd": "Forgot Password?",
      "login_or_sign_in_with": "or Sign In with",
      "login_do_not_an_account": "Don't have an account?",
      "login_signup": "Sign Up",
      "signup_display_name": "Enter Your Display Name",
      "signup_email_address": "Enter Email Address",
      "signup_create_pwd": "Create 8 Digits Password",
      "signup_confirm_pwd": "Confirm Password",
      "signup_term_condition": "I accept the Terms and Conditions and the Privacy Policy",
      "signup_signup": "Sign Up",
      "signup_or_signup_with": "or Sign Up with",
      "signup_already_have_an_account": "Already have an account",
      "signup_signin": "Sign In",
      "forgot_enter_email": "Please enter your e-mail",
      "forgot_email": "E-mail",
      "forgot_continue": "Continue",
      "otp_enter_otp": "Enter OTP",
      "otp_digit_code_send": "Enter the 6-digit code send to",
      "otp_continue": "Continue",
      "otp_resend_otp": "Resend OTP",
      "otp_code_valid": "OTP code valid for",
      "profile_enter_name": "Enter Name",
      "profile_email_address": "Enter Email Address",
      "profile_mobile_number": "Mobile Number",
      "profile_dob": "DOB",
      "profile_country": "Country",
      "profile_city": "City",
      "profile_update_btn": "Update",
      "profile_dlt_btn": "Delete Account?",
      "profile_my_profile": "My Profile",
      "change_pwd_change_pwd": "Change Password",
      "change_pwd_new_pwd": "New Password",
      "change_pwd_confirm_pwd": "Confirm Password",
      "change_pwd_update_pwd": "Update Password",
      "buy_select_subscription": "Please Select Your \n Subscription",
      "buy_restore_subscription": "Restore Purchase",
      "buy_pay_now": "Pay Now",
      "buy_in_case_query": "In case of any query, email us at info@YojmaTv.net",
      "order_history_title": "Order History",
      "order_history_payment_mode": "Payment Mode",
      "order_history_payment_status": "Payment Status",
      "order_history_order_Id": "Order Id",
      "order_history_transaction_type": "Transaction Type",
      "settings_title": "Settings",
      "settings_change_lang": "Change Language",
      "settings_streaming_settings": "Video Quality",
      "settings_content_preferences": "Content Preferences",
      "streaming_settings_title": "Video Quality",
      "streaming_auto": "Auto",
      "streaming_hd": "HD",
      "streaming_full_hd": "Full HD",
      "streaming_sd": "SD",
      "lang_change_lang": "Change Language",
      "lang_english": "English",
      "lang_spanish": "Spanish",
      "could_not_find_any_result": "Sorry! we could not find any results.",
      "home_tabbar": "Home",
      "reel_tabbar": "Reel",
      "live_tabbar": "LIVE",
      "vod_tabbar": "VOD",
      "detail_page_episodes": "Episodes",
      "detail_page_related_videos": "Related Videos",
      "detail_page_produced_by": "Produced by",
      "detail_page_sponsored_by": "Sponsored by",
      "detail_page_my_list": "My List",
      "detail_page_share": "Share",
      "detail_page_like": "Like",
      "detail_page_play": "Play",
      "detail_page_trailer": "Watch Trailer",
      "skip": "Skip",
      "noti_title": "Notifications",
      "noti_no_new_notifications": "Notifications",
      "popular_search": "Popular Searches",
      "recent_searches": "Recent Searches",
      "cancel_search": "Cancel",
      "no_result": "No results found",
      "more_gaming": "Gaming",
      "my_list": "My List",
      "more_account": "Account",
      "more_settings": "Settings",
      "more_buy_now": "Buy Now",
      "more_order_history": "Order History",
      "more_privacy_policy": "Privacy Policy",
      "more_contact_us": "Contact Us",
      "more_term_condition": "Terms & Conditions",
      "more_video_quality": "Video Quality",
      "more_manage_subscription": "Manage Subscription",
      "account_edit_profile": "Edit Profile",
      "account_change_password": "Change Password",
      "account_logout": "Logout",
      "popup_username_pwd_does_not_match": "Username or Password doesn't match.",
      "popup_request_sent": "Request Sent",
      "popup_thanks_for_putting_request": "Thanks for putting the request. If we find the email address in our system, we will send the reset link over the mail please enter new password",
      "popup_check_your_email": "Check your email",
      "popup_pwd_must_be_8_to_16_char": "Password must be 8-16 characters, at least 1 number, 1 lowercase letter & 1 uppercase letter",
      "popup_user_already_has_an_account": "User already has an account with this email or credential.",
      "popup_error": "Error",
      "popup_mobile_number_digit": "Mobile number should be 9 digit",
      "popup_update": "Updated",
      "popup_update_successfully": "Update successfully",
      "popup_delete_account": "Delete Account",
      "popup_want_to_delete_account": "Are you sure do you want to delete your account?",
      "popup_continue": "Continue",
      "popup_cancel": "Cancel",
      "popup_under_review": "Under Review",
      "popup_your_previous_account_already_review": "Your Previous Account deletion request is already under review. Our team will get back with the details on the same",
      "popup_pls_enter_new_pwd": "Please enter New Password",
      "popup_pwd_pwd_changed": "Password Changed",
      "popup_pwd_has_been_changed": "Your password has been changed successfully",
      "popup_check_internet_connection": "It seems like there is a problem with your internet connection. Please check your\nconnection and try again",
      "popup_no_internet_connection_found": "No internet connection found.\nCheck your connection.",
      "popup_remove_content_from_my_list": "Are you sure do you want to remove this content from My list?",
      "popup_no_new_notification": "No new notifications",
      "popup_recent_search": "Recent Searches",
      "popup_delete_search_history": "Are you sure you want to delete the search history?",
      "popup_search_yes": "Yes",
      "popup_search_no": "No",
      "popup_subscribe_access_to_premium": "Access to premium content is just a click away. Please visit mobile apps or website",
      "popup_subscribe_purchase": "Purchase",
      "popup_logout": "Log Out",
      "popup_logout_you_want_to_logout": "Are you sure you want to logout?",
      "popup_change_language_tittle": "Change Language",
      "popup_do_you_want_to_change_lang": "Do you want to change language",
      "popup_invalid_otp": "Invalid OTP",
      "popup_enter_valid_otp": "Invalid OTP, please enter valid one.",
      "popup_expire_time": "Time Expire",
      "popup_please_click_on_the_resend_button": "Please click on the resend button to get new OTP",
      "popup_empty_email_tittle": "Empty Email",
      "popup_empty_email_subtitle": "Please Enter the Email Address",
      "popup_invalid_email_tittle": "Invalid Email",
      "popup_invalid_email_subtitle": "Please Enter a valid Email Address",
      "popup_continue_btn": "Continue",
      "popup_incorrect_pwd_tittle": "Incorrect Password",
      "popup_login_enter_pwd_tittle": "Please enter Password",
      "popup_profile_error": "Error",
      "popup_something_went_wrong": "Something went wrong",
      "popup_change_pwd_enter_confirm_pwd": "Please enter Confirm Password",
      "popup_change_pwd_your_pwd_does_not_match": "Sorry, your password doesn't match please check your password again",
      "popup_user_not_verify": "You need to verify your account to access the selected content",
      "popup_verify": "Verify",
      "popup_select_plan": "Access to premium content is just a click away. Please select",
      "popup_ok": "OK",
      "popup_minutes": "min",
      "popup_purchase": "Purchase",
      "popup_remove": "Remove",
      "popup_user_does_not_exists": "User with this email id does not exist",
      "popup_payment_error": "There was an error processing your request, please try after some time. If additional support is required, please contact us at",
      "popup_payment_success": "Payment Completed, we’ve send you a e-mail, please confirm your account to login",
      "popup_confirm_pwd": "Confirm Password",
      "popup_your_account_has_been_verified": "Your Account Has been Verified Successfully",
      "popup_date_difference": "You must be 18 years old and above.",
      "popup_payment_description": "We’ve sent you an e-mail, please enter in your inbox and confirm your account to be able to login Bread Gang TV",
      "popup_empty_Password": "Empty password",
      "popup_empty_Confirm_Password": "Empty confirm password",
      "popup_invalid_Confirm_Password": "Invalid confirm password",
      "podcast_tabbar": "Podcast",
      "kids_tabbar": "Kids",
      "series_tabbar": "Series",
      "movie_tabbar": "Movie",
      "more_tabbar": "More",
      "gaming_tabbar": "Gaming",
      "more_title_btn": "More",
      "detail_page_no_data_available": "No data available",
      "related_data_see_all": "See all",
      "detail_page_now_playing": "Now playing",
      "search_hint": "Search",
      "search_result": "Search result",
      "detail_page_all_episode": "All Episode",
      "detail_page_season": "Season",
      "no_connection_title": "You’re Offline",
      "no_connection_description": "It seems like there is a problem with your\n internet connection. Please check your\n connection and try again",
      "no_connection_btn_txt": "Reload App",
      "popup_empty_dob_tittle": "Empty Dob",
      "popup_empty_dob_subtitle": "Please Enter the Dob",
      "email_verify_title": "Verify",
      "email_verified_title": "Verified",
      "popup_continue_watching": "Continue Watching",
      "popup_continue_watching_for": "Continue watching for",
      "popup_change_pwd_incorrect_confirm_pwd": "Incorrect confirm Password",
      "search_see_all": "See all",
      "search_movies": "Movies",
      "search_documentaries": "Documentaries",
      "search_results": "Results",
      "rate_the_app": "Rate the app"
    }
  },
  "responseCode": 2000,
  "debugMessage": null
}